files/__init__.py
files/create_table.py
files/delete.py
files/display.py
files/drop_table.py
files/insert.py
files/update.py
studentProfile/__init__.py
studentProfile/create_table.py
studentProfile/delete.py
studentProfile/display.py
studentProfile/drop_table.py
studentProfile/insert.py
studentProfile/update.py
studentProfile-0.0.4.dist-info/METADATA
studentProfile-0.0.4.dist-info/WHEEL
studentProfile-0.0.4.dist-info/entry_points.txt
studentProfile-0.0.4.dist-info/top_level.txt
studentProfile-0.0.4.dist-info/RECORD
