Metadata-Version: 2.1
Name: studentProfile
Version: 0.0.4
Summary: Database entry for student profile
Author: Sonarjit
